crispy/__init__.py
crispy/crispy.py
crispy/duplicate_name_exception.py
crispy/missing_value_exception.py
crispy/no_arguments_exception.py
crispy/parsing_exception.py
crispy/too_many_subcommands_exception.py
crispy/unexpected_argument_exception.py
crispy_parser-2.1.0.dist-info/LICENSE
crispy_parser-2.1.0.dist-info/METADATA
crispy_parser-2.1.0.dist-info/WHEEL
crispy_parser-2.1.0.dist-info/top_level.txt
crispy_parser-2.1.0.dist-info/RECORD
