Metadata-Version: 2.1
Name: crispy-parser
Version: 2.1.0
Summary: Crispy is a simple command line argument parser, ready to be integrated to any project of any size!
Home-page: https://github.com/fybx/crispy
Author: F. Y. BALABAN, <fyb@fybx.dev>
Author-email: fyb@fybx.dev
License: GNU LGPL-v2.1
Requires-Python: >=3.7
License-File: LICENSE
